pymatex/__init__.py
pymatex/error/ExceptionErrorListener.py
pymatex/error/__init__.py
pymatex/grammar/MatexLexer.py
pymatex/grammar/MatexParser.py
pymatex/grammar/MatexParserListener.py
pymatex/grammar/__init__.py
pymatex/listener/MatexAST.py
pymatex/listener/MatexASTVisitor.py
pymatex/listener/__init__.py
pymatex/node/Addition.py
pymatex/node/BinaryOperator.py
pymatex/node/Constant.py
pymatex/node/Division.py
pymatex/node/Exponentiation.py
pymatex/node/Fraction.py
pymatex/node/Function.py
pymatex/node/IndexedVariable.py
pymatex/node/Inequality.py
pymatex/node/Integral.py
pymatex/node/IterativeFunction.py
pymatex/node/Multiplication.py
pymatex/node/Negate.py
pymatex/node/Node.py
pymatex/node/Product.py
pymatex/node/Set.py
pymatex/node/Subtraction.py
pymatex/node/Summation.py
pymatex/node/Variable.py
pymatex/node/__init__.py
pymatex/search/IndexCreatorVisitor.py
pymatex/search/IndexSearchVisitor.py
pymatex/search/SearchQuery.py
pymatex/search/SimilarityMatrix.py
pymatex/search/__init__.py
tests/BaseTest.py
tests/__init__.py
tests/listener/MatexASTVisitor.py
tests/listener/__init__.py
tests/node/Additive.py
tests/node/Constant.py
tests/node/Exponentiation.py
tests/node/Function.py
tests/node/Inequality.py
tests/node/Invalid.py
tests/node/IterativeFunction.py
tests/node/Lambert.py
tests/node/Multiplicative.py
tests/node/Other.py
tests/node/Set.py
tests/node/TaylorMaclaurin.py
tests/node/Variable.py
tests/node/__init__.py
tests/search/IndexCreatorVisitor.py
tests/search/SearchQuery.py
tests/search/SimilarityMatrix.py
tests/search/__init__.py
pymatex-0.0.15.dist-info/LICENSE
pymatex-0.0.15.dist-info/METADATA
pymatex-0.0.15.dist-info/WHEEL
pymatex-0.0.15.dist-info/top_level.txt
pymatex-0.0.15.dist-info/RECORD
