Metadata-Version: 2.1
Name: pymatex
Version: 0.0.15
Summary: Parser which allows to parse mathematical expressions written in LaTeX
Home-page: https://github.com/Gawaboumga/PyMatex
Author: Gawaboumga
License: UNKNOWN
Platform: UNKNOWN
Classifier: Programming Language :: Python :: 3
Classifier: License :: OSI Approved :: MIT License
Classifier: Operating System :: OS Independent
Requires-Dist: antlr4-python3-runtime
